.gitignore
CHANGELOG
LICENCE
Makefile
README.md
VERSION
project.qbs
setup.cfg
setup.py
./VERSION
.github/workflows/cicd.yaml
examples/hello_gap.py
gap_client/__init__.py
gap_client/helpers.py
gap_client.egg-info/PKG-INFO
gap_client.egg-info/SOURCES.txt
gap_client.egg-info/dependency_links.txt
gap_client.egg-info/requires.txt
gap_client.egg-info/top_level.txt
gap_client.egg-info/zip-safe
requirements/requirements.in
requirements/requirements.txt
requirements/test_requirements.in
requirements/test_requirements.txt
tests/Makefile
tests/__init__.py
tests/common.py
tests/pytest.ini
tests/data/SoA.csv
tests/integration/__init__.py
tests/integration/test_gap.py
tests/load/__init__.py
tests/unit/__init__.py