Metadata-Version: 2.1
Name: gap-client
Version: 0.1.1
Summary: API for compliance tool
Home-page: https://github.com/arribatec-cloud-1/gap-client
Author: Gap Solutions
Author-email: pypi@gapsolutions.dk
Maintainer: Gap Solutions
Maintainer-email: pypi@gapsolutions.dk
License: Proprietary
Download-URL: https://pypi.org/project/gap-client/
Project-URL: Docs, https://github.com/arribatec-cloud-1/gap-client/blob/main/README.md
Keywords: python3,compliance
Platform: Linux
Classifier: Development Status :: 3 - Alpha
Classifier: Intended Audience :: Developers
Classifier: Intended Audience :: Other Audience
Classifier: Topic :: Utilities
Classifier: Natural Language :: English
Classifier: Operating System :: POSIX :: Linux
Classifier: Programming Language :: Python :: 3.9
Classifier: Topic :: Other/Nonlisted Topic
Requires-Python: >=3.9.20
License-File: LICENCE
